{
  "v": "7.0.1",
  "p": {
    "autoAdjustIndex": true,
    "hierarchicalRendering": false
  },
  "a": {
    "rotateAsClock": false,
    "connectActionType": "host",
    "width": 1920,
    "fitContent": false,
    "height": 1080,
    "previewURL": "display-electric.html",
    "rectSelectable": false,
    "pannable": false,
    "zoomable": false
  },
  "d": [
    {
      "c": "ht.Block",
      "i": 18238,
      "p": {
        "position": {
          "x": 910,
          "y": 51.54842
        },
        "width": 422.90768,
        "height": 35
      }
    },
    {
      "c": "ht.Node",
      "i": 23212,
      "p": {
        "displayName": "image",
        "image": "symbols/html/image.json",
        "position": {
          "x": 960,
          "y": 53.90723
        },
        "width": 396.23159,
        "height": 30.28238
      },
      "a": {
        "imageURL": "assets/ioe.png"
      }
    }
  ],
  "modified": "Wed May 08 2019 17:44:48 GMT+0900 (한국 표준시)",
  "contentRect": {
    "x": 0,
    "y": 0,
    "width": 1920,
    "height": 1080
  }
}