{
  "modified": "Fri Mar 15 2019 15:13:34 GMT+0800 (中国标准时间)",
  "background": "rgb(61,61,61)",
  "width": 170,
  "height": 190,
  "attachStyle": "close",
  "comps": [
    {
      "type": "shape",
      "gradientPack": [
        "L",
        4691.6973,
        605.7469,
        4432.6533,
        864.7906,
        0.58372,
        -0.3363,
        0.59802,
        0.34528,
        -3017.83818,
        1316.38172,
        0,
        "#E9F8FF",
        0.9967,
        "rgba(233, 248, 255, 0)"
      ],
      "pixelPerfect": true,
      "opacity": 0.49,
      "points": [
        161.23712,
        44.41695,
        84.93094,
        88.40521,
        8.76288,
        44.41695,
        83.06645,
        1.60262,
        161.23712,
        44.41695
      ],
      "segments": [
        1,
        2,
        2,
        2,
        2,
        5
      ]
    },
    {
      "type": "shape",
      "gradientPack": [
        "L",
        3840.2527,
        -2565.4917,
        4013.0183,
        -2392.7261,
        0.60955,
        0.35218,
        0,
        0.69055,
        -2360.45232,
        415.18589,
        0,
        "#E9F8FF",
        0.9967,
        "rgba(233, 248, 255, 0)"
      ],
      "pixelPerfect": true,
      "opacity": 0.49,
      "points": [
        85,
        174.86253,
        8.76288,
        130.80521,
        8.76288,
        44.41695,
        85,
        88.47427,
        85,
        174.86253
      ],
      "segments": [
        1,
        2,
        2,
        2,
        2,
        5
      ]
    },
    {
      "type": "shape",
      "gradientPack": [
        "L",
        -2585.9851,
        685.4216,
        -2360.2241,
        911.1825,
        -0.60955,
        0.35218,
        0,
        0.69055,
        -1376.14194,
        415.18589,
        0,
        "#E9F8FF",
        0.9967,
        "rgba(233, 248, 255, 0)"
      ],
      "pixelPerfect": true,
      "opacity": 0.49,
      "points": [
        85,
        174.86253,
        161.23712,
        130.80521,
        161.23712,
        44.41695,
        85,
        88.47427,
        85,
        174.86253
      ],
      "segments": [
        1,
        2,
        2,
        2,
        2,
        5
      ]
    },
    {
      "type": "shape",
      "gradientPack": [
        "L",
        4558.2314,
        776.9145,
        4485.7603,
        776.9145,
        0.58372,
        -0.3363,
        0.59802,
        0.34528,
        -3017.83818,
        1316.38172,
        0,
        "#0055FF",
        1,
        "#00CDFF"
      ],
      "pixelPerfect": true,
      "opacity": 0.5,
      "points": [
        128.57393,
        64.02867,
        86.243,
        88.40521,
        44.05017,
        64.02867,
        85.20717,
        40.27362,
        128.57393,
        64.02867
      ],
      "segments": [
        1,
        2,
        2,
        2,
        2,
        5
      ]
    },
    {
      "type": "shape",
      "gradientPack": [
        "L",
        3963.5312,
        -2477.5352,
        4004.7112,
        -2498.5364,
        0.60955,
        0.35218,
        0,
        0.69055,
        -2360.45232,
        415.18589,
        0,
        "#193DF7",
        1,
        "#2B06C2"
      ],
      "pixelPerfect": true,
      "opacity": 0.5,
      "points": [
        86.31205,
        136.32963,
        44.05017,
        111.88404,
        44.05017,
        64.02867,
        86.31205,
        88.47427,
        86.31205,
        136.32963
      ],
      "segments": [
        1,
        2,
        2,
        2,
        2,
        5
      ]
    },
    {
      "type": "shape",
      "gradientPack": [
        "L",
        -2418.1238,
        777.0395,
        -2459.3037,
        798.0408,
        -0.60955,
        0.35218,
        0,
        0.69055,
        -1376.14194,
        415.18589,
        0,
        "#193DF7",
        1,
        "#2B06C2"
      ],
      "pixelPerfect": true,
      "opacity": 0.5,
      "points": [
        86.31205,
        136.32963,
        128.57393,
        111.88404,
        128.57393,
        64.02867,
        86.31205,
        88.47427,
        86.31205,
        136.32963
      ],
      "segments": [
        1,
        2,
        2,
        2,
        2,
        5
      ]
    },
    {
      "type": "shape",
      "gradientPack": [
        "L",
        4519.6572,
        795.6949,
        4485.8516,
        795.6949,
        0.58372,
        -0.3363,
        0.59802,
        0.34528,
        -3017.83818,
        1316.38172,
        0,
        "#0055FF",
        1,
        "#00CDFF"
      ],
      "pixelPerfect": true,
      "opacity": 0.5,
      "points": [
        105.99283,
        77.01108,
        86.243,
        88.33616,
        66.56222,
        76.94202,
        85.82866,
        65.89316,
        105.99283,
        77.01108
      ],
      "segments": [
        1,
        2,
        2,
        2,
        2,
        5
      ]
    },
    {
      "type": "shape",
      "gradientPack": [
        "L",
        3990.374,
        -2500.395,
        4009.5835,
        -2510.1914,
        0.60955,
        0.35218,
        0,
        0.69055,
        -2360.45232,
        415.18589,
        0,
        "#193DF7",
        1,
        "#2B06C2"
      ],
      "pixelPerfect": true,
      "opacity": 0.5,
      "points": [
        86.31205,
        110.7101,
        66.56222,
        99.31596,
        66.56222,
        77.01108,
        86.31205,
        88.33616,
        86.31205,
        110.7101
      ],
      "segments": [
        1,
        2,
        2,
        2,
        2,
        5
      ]
    },
    {
      "type": "shape",
      "gradientPack": [
        "L",
        -2407.9768,
        762.6943,
        -2427.1863,
        772.4909,
        -0.60955,
        0.35218,
        0,
        0.69055,
        -1376.14194,
        415.18589,
        0,
        "#193DF7",
        1,
        "#2B06C2"
      ],
      "pixelPerfect": true,
      "opacity": 0.5,
      "points": [
        86.31205,
        110.7101,
        105.99283,
        99.31596,
        105.99283,
        77.01108,
        86.31205,
        88.33616,
        86.31205,
        110.7101
      ],
      "segments": [
        1,
        2,
        2,
        2,
        2,
        5
      ]
    }
  ]
}